{
  "0": {
    "International Station": [
      "Mediterranean Week 🥙"
    ],
    "Comfort Food": [
      "Roasted Italian Chicken Thigh"
    ],
    "Mindful": [
      "Maple Chili Glazed Pork Loin"
    ],
    "Sides": [
      "Brocolini",
      "Cous Cous Primavera"
    ],
    "Soup": [
      "Veggie Chili",
      "Chicken Noodle"
    ]
  },
  "5": {
    "International Station": [
      "Pasta Week 🍝"
    ],
    "Comfort Food": [
      "Veggie Chilaquilles"
    ],
    "Mindful": [
      "Thai Chicken Stir Fry"
    ],
    "Sides": [
      "Roasted Carrots",
      "Cilantro Lime Rice"
    ],
    "Soup": [
      "Tomato Basil",
      "Broccoli Cheddar"
    ]
  },
  "6": {
    "International Station": [
      "Pasta Week 🍝"
    ],
    "Comfort Food": [
      "Beef and Mushroom Stroganoff w/ Pasta"
    ],
    "Mindful": [
      "Tortilla Crusted Tilapia"
    ],
    "Sides": [
      "Sugar Snap Peas",
      "Orzo"
    ],
    "Soup": [
      "Tomato Basil",
      "Broccoli Cheddar"
    ]
  },
  "7": {
    "International Station": [
      "Pasta Week 🍝"
    ],
    "Comfort Food": [
      "Spinach Ravioli with Cream Sauce"
    ],
    "Mindful": [
      "Baked Turkey Meatloaf w/ Turkey Gravy"
    ],
    "Sides": [
      "Satueed Brocolini",
      "Roasted Sweet Potatoes"
    ],
    "Soup": [
      "Tomato Basil",
      "Broccoli Cheddar"
    ]
  },
  "8": {
    "International Station": [
      "Pasta Week 🍝"
    ],
    "Comfort Food": [
      "Chopped Steak with Onions"
    ],
    "Mindful": [
      "Piri Piri Chicken"
    ],
    "Sides": [
      "Jollof Rice",
      "Githeri"
    ],
    "Soup": [
      "Tomato Basil",
      "Broccoli Cheddar"
    ]
  },
  "11": {
    "International Station": [
      "Burrito Bowl"
    ],
    "Comfort Food": [
      "Open faced Pot Roast Sandwich"
    ],
    "Mindful": [
      "Chicken Breast with Bruchetta"
    ],
    "Sides": [
      "Snow Peas",
      "Roasted Red Potatoes"
    ],
    "Soup": [
      "Veggie Chili",
      "Corn Chowder"
    ]
  },
  "12": {
    "International Station": [
      "Burrito Bowl"
    ],
    "Comfort Food": [
      "Cheese Tortellini Breadstick"
    ],
    "Mindful": [
      "Biryani Chicken"
    ],
    "Sides": [
      "Lemon Pepper Green Beans",
      "Yellow Rice"
    ],
    "Soup": [
      "Veggie Chili",
      "Corn Chowder"
    ]
  },
  "13": {
    "International Station": [
      "Burrito Bowl"
    ],
    "Comfort Food": [
      "Dijon Chicken"
    ],
    "Mindful": [
      "Baked Herbed Cod"
    ],
    "Sides": [
      "Asparagus",
      "Scalloped Potatoes"
    ],
    "Soup": [
      "Veggie Chili",
      "Corn Chowder"
    ]
  },
  "14": {
    "International Station": [
      "Burrito Bowl"
    ],
    "Comfort Food": [
      "Spicy Whole Wheat Spaghetti"
    ],
    "Mindful": [
      "Tempura Chicken Stir Fry w/ Rice"
    ],
    "Sides": [
      "Roasted Cauliflower",
      "Spring Roll"
    ],
    "Soup": [
      "Veggie Chili",
      "Com Chowder"
    ]
  },
  "15": {
    "International Station": [
      "Burrito Bowl"
    ],
    "Comfort Food": [
      "Mac & Cheese"
    ],
    "Mindful": [
      "Fried Chicken"
    ],
    "Sides": [
      "Corn bread",
      "Collard Greens"
    ],
    "Soup": [
      "Veggie Chili",
      "Corn Chowder"
    ]
  },
  "18": {
    "International Station": [
      "Mac & Cheese"
    ],
    "Comfort Food": [
      "BBQ Pulled Chicken Sandwich"
    ],
    "Mindful": [
      "Teriyaki Glazed Salmon"
    ],
    "Sides": [
      "Corn",
      "Roasted Potatoes"
    ],
    "Soup": [
      "Tomato Basil",
      "Chicken Tortilla"
    ]
  },
  "19": {
    "International Station": [
      "Mac & Cheese"
    ],
    "Comfort Food": [
      "Home Made Beef Meatloaf"
    ],
    "Mindful": [
      "Chicken Picata"
    ],
    "Sides": [
      "Roasted Carrots and Broccoli",
      "Mashed Potatoes"
    ],
    "Soup": [
      "Tomato Basil",
      "Chicken Tortilla"
    ]
  },
  "20": {
    "International Station": [
      "Mac & Cheese"
    ],
    "Comfort Food": [
      "Swedish Meatballs w/ Eggnoodles"
    ],
    "Mindful": [
      "Veggie Lo Mein"
    ],
    "Sides": [
      "Roasted Vegetables",
      "Egg roll"
    ],
    "Soup": [
      "Tomato Basil",
      "Chicken Tortilla"
    ]
  },
  "21": {
    "International Station": [
      "Mac & Cheese"
    ],
    "Comfort Food": [
      "Chipotle & Orange Grilled Chicken"
    ],
    "Mindful": [
      "Tofu Stir Fry"
    ],
    "Sides": [
      "Lemon Pepper Green Beans",
      "Rice"
    ],
    "Soup": [
      "Tomato Basil",
      "Chicken Tortilla"
    ]
  },
  "22": {
    "International Station": [
      "Mac & Cheese"
    ],
    "Comfort Food": [
      "Baked Battered Cod"
    ],
    "Mindful": [
      "Jerk Chicken"
    ],
    "Sides": [
      "Plantains",
      "Rice and Pigeon Peas"
    ],
    "Soup": [
      "Tomato Basil",
      "Chicken Tortilla"
    ]
  },
  "25": {
    "International Station": [
      "Mediterranean Week 🥙"
    ],
    "Comfort Food": [
      "Baked Mostaccioli"
    ],
    "Mindful": [
      "Lemon Garlic Baked Chicken"
    ],
    "Sides": [
      "Roasted Carrots",
      "Roasted Red Potatoes"
    ],
    "Soup": [
      "Veggie Chili",
      "Chicken Noodle"
    ]
  },
  "26": {
    "International Station": [
      "Mediterranean Week 🥙"
    ],
    "Comfort Food": [
      "Chicken Tikka Masala"
    ],
    "Mindful": [
      "Blackened Tilapia"
    ],
    "Sides": [
      "Roasted Cauliflower",
      "Rice"
    ],
    "Soup": [
      "Veggie Chili",
      "Chicken Noodle"
    ]
  },
  "27": {
    "International Station": [
      "Mediterranean Week 🥙"
    ],
    "Comfort Food": [
      "Baked Chicken Parmesean w/ Pasta"
    ],
    "Mindful": [
      "Turkey Breast Vesuvio"
    ],
    "Sides": [
      "Roasted Zuccini",
      "Mashed Potatoes"
    ],
    "Soup": [
      "Veggie Chili",
      "Chicken Noodle"
    ]
  }
}